rweintr_wordgame/__init__.py
rweintr_wordgame/__main__.py
rweintr_wordgame/config.toml
rweintr_wordgame/game_models.py
rweintr_wordgame/game_scoring.py
rweintr_wordgame/wordgame.py
rweintr_wordgame/data/wgplayers.db
rweintr_wordgame-1.1.4.dist-info/METADATA
rweintr_wordgame-1.1.4.dist-info/WHEEL
rweintr_wordgame-1.1.4.dist-info/entry_points.txt
rweintr_wordgame-1.1.4.dist-info/top_level.txt
rweintr_wordgame-1.1.4.dist-info/RECORD
