Metadata-Version: 2.4
Name: rweintr_wordgame
Version: 1.1.4
Summary: Solve hidden word by guessing letters in it
Author-email: rweintr <rweintr@gmail.com>
Keywords: word,game
Classifier: Programming Language :: Python
Classifier: Programming Language :: Python :: 3
Classifier: Environment :: Console
Classifier: Topic :: Games/Entertainment :: Puzzle Games
Requires-Dist: wonderwords>=2.2.0
Requires-Dist: SQLAlchemy>=2.0.44
Provides-Extra: dev
Requires-Dist: bumpver; extra == "dev"
Requires-Dist: pip-tools; extra == "dev"
